{"blocks":{"languageVersion":0,"blocks":[{"type":"controls_whileUntil","id":"s]s0z}|wh]%C3^JXM{zo","x":-90,"y":-1030,"fields":{"MODE":"WHILE"},"inputs":{"BOOL":{"block":{"type":"logic_boolean","id":"*0wKJ_mkJ(4y4~ADMD]0","fields":{"BOOL":"TRUE"}}},"DO":{"block":{"type":"variables_set","id":"cYX;wks^t3Sl[Fg9mElQ","fields":{"VAR":{"id":"wlplZ9BSF*Z|)*^h#f%["}},"inputs":{"VALUE":{"block":{"type":"utils_current_time","id":",_tg;h9x-=;al`tb$y86"}}},"next":{"block":{"type":"variables_set","id":"xf!/LQ@G-8I;?HxCi=u[","fields":{"VAR":{"id":"5~Ymb/.DimsOP1QPM8Ms"}},"inputs":{"VALUE":{"block":{"type":"text_getSubstring","id":"V0g5[@7z~AxS0f,7$$7$","extraState":"<mutation at1=\"false\" at2=\"true\"></mutation>","fields":{"WHERE1":"FIRST","WHERE2":"FROM_START"},"inputs":{"STRING":{"block":{"type":"variables_get","id":"~7~}`m@FPPmkz`P[gJF$","fields":{"VAR":{"id":"wlplZ9BSF*Z|)*^h#f%["}}}},"AT2":{"block":{"type":"math_number","id":"`Y0Yh-HR*CTqBY%=$E;$","fields":{"NUM":10}}}}}}},"next":{"block":{"type":"variables_set","id":"d$TpVW9S-IhquY!6Ib%b","fields":{"VAR":{"id":"x,M;=_:Nol4(h}TFm_2$"}},"inputs":{"VALUE":{"block":{"type":"text_getSubstring","id":"D].)*MW^EH_{MCKlCnh+","extraState":"<mutation at1=\"true\" at2=\"false\"></mutation>","fields":{"WHERE1":"FROM_START","WHERE2":"LAST"},"inputs":{"STRING":{"block":{"type":"variables_get","id":"uC6y5MWmGdfZJgQ^*/o=","fields":{"VAR":{"id":"wlplZ9BSF*Z|)*^h#f%["}}}},"AT1":{"block":{"type":"math_number","id":"O.rEf;9k!puscY-Jdni0","fields":{"NUM":12}}}}}}},"next":{"block":{"type":"variables_set","id":"LoB~t^;XkAH6FoGj=iXl","fields":{"VAR":{"id":"+fYZf.{A7MdWp~[695K("}},"inputs":{"VALUE":{"block":{"type":"text_getSubstring","id":"SoN]+[srjO7%a`(C*JS1","extraState":"<mutation at1=\"true\" at2=\"true\"></mutation>","fields":{"WHERE1":"FROM_START","WHERE2":"FROM_START"},"inputs":{"STRING":{"block":{"type":"variables_get","id":"CU9(,gl[BrwPU#hBKQ|H","fields":{"VAR":{"id":"wlplZ9BSF*Z|)*^h#f%["}}}},"AT1":{"block":{"type":"math_number","id":"C%qAE^Kei)F%fiWk;n_y","fields":{"NUM":12}}},"AT2":{"block":{"type":"math_number","id":"Ntsctpo^e6ni1k{Y{-U)","fields":{"NUM":13}}}}}}},"next":{"block":{"type":"variables_set","id":"7f4G5*PZLs[S,Ae,k.2a","fields":{"VAR":{"id":"qx-Tk#g3SNygx}Km%?eW"}},"inputs":{"VALUE":{"block":{"type":"text_getSubstring","id":"cg7gqJ!(q{MTJkm+,Bnv","extraState":"<mutation at1=\"true\" at2=\"true\"></mutation>","fields":{"WHERE1":"FROM_START","WHERE2":"FROM_START"},"inputs":{"STRING":{"block":{"type":"variables_get","id":"uozYB#{@4`xF@lqoTe+4","fields":{"VAR":{"id":"wlplZ9BSF*Z|)*^h#f%["}}}},"AT1":{"block":{"type":"math_number","id":"xR$E-,%b+h_r,q~r)0J7","fields":{"NUM":15}}},"AT2":{"block":{"type":"math_number","id":"8(@K`YgwKwL}%%xt{mSg","fields":{"NUM":16}}}}}}},"next":{"block":{"type":"variables_set","id":"GPx[87V,@}dx!l8jd~en","fields":{"VAR":{"id":"v3(@jXBkl2uoQIC_{ISq"}},"inputs":{"VALUE":{"block":{"type":"text_getSubstring","id":"9NUq$~v!cZY0@Te_S{50","extraState":"<mutation at1=\"true\" at2=\"false\"></mutation>","fields":{"WHERE1":"FROM_START","WHERE2":"LAST"},"inputs":{"STRING":{"block":{"type":"variables_get","id":"RpoNNFs|Few,ok5y54cl","fields":{"VAR":{"id":"wlplZ9BSF*Z|)*^h#f%["}}}},"AT1":{"block":{"type":"math_number","id":"8C_qCo4=M-[2^)VG3}+1","fields":{"NUM":18}}}}}}},"next":{"block":{"type":"text_print","id":"0uqdaJ:090P]gcSat#[@","inputs":{"TEXT":{"shadow":{"type":"text","id":"kx@-|I$P8~Kq3iiXQ+pH","fields":{"TEXT":"가나다"}},"block":{"type":"variables_get","id":"h6mcI%@dGj4kO)IEjh|H","fields":{"VAR":{"id":"wlplZ9BSF*Z|)*^h#f%["}}}}},"next":{"block":{"type":"oled_set_font","id":"hLY);f6EI/$R]vzXq@9=","inputs":{"size":{"shadow":{"type":"math_number","id":"i/h|{cd@!y[.9VX2R`vU","fields":{"NUM":15}}}},"next":{"block":{"type":"oled_draw_line","id":"K^7A2}EO_?!)NC]aN2,C","inputs":{"x1":{"shadow":{"type":"math_number","id":"Dy9i[+?#L@qVRycs`X39","fields":{"NUM":20}}},"y1":{"shadow":{"type":"math_number","id":"P-k6%BbKn{YwQK=9UTy`","fields":{"NUM":25}}},"x2":{"shadow":{"type":"math_number","id":"%+smgp}02H!aV5N^V~Bx","fields":{"NUM":100}}},"y2":{"shadow":{"type":"math_number","id":"`ZKnNh1()t5#,T{pCWC7","fields":{"NUM":25}}}},"next":{"block":{"type":"oled_draw_text","id":"+.k(-rxS4vMT?l+66z`K","inputs":{"x":{"shadow":{"type":"math_number","id":"V.W)/(XE,7..u;;T$zI:","fields":{"NUM":20}}},"y":{"shadow":{"type":"math_number","id":"Js,|044Ztf%OZynNjtxe","fields":{"NUM":5}}},"text":{"shadow":{"type":"text","id":"*[_af@^]/zDoxVsB61]-","fields":{"TEXT":"안녕하세요"}},"block":{"type":"variables_get","id":"xWHZx;;doA+fE8fcyzM?","fields":{"VAR":{"id":"5~Ymb/.DimsOP1QPM8Ms"}}}}},"next":{"block":{"type":"oled_set_font","id":"aR?rz.o?-2QT+`|JM.uR","inputs":{"size":{"shadow":{"type":"math_number","id":"4x,*AK_RV0!K!C67QG`z","fields":{"NUM":30}}}},"next":{"block":{"type":"oled_draw_text","id":"D%PA@_/[T]703;.C}zi?","inputs":{"x":{"shadow":{"type":"math_number","id":"h=op-v:@C15KN(N:I5]$","fields":{"NUM":0}}},"y":{"shadow":{"type":"math_number","id":"M(:6#=7WGOex?BX6[Mz^","fields":{"NUM":30}}},"text":{"shadow":{"type":"text","id":"rQn|8{lS.U-y1dGI^bvX","fields":{"TEXT":"안녕하세요"}},"block":{"type":"variables_get","id":"=SRS2yzbb^X]xa:g?5H^","fields":{"VAR":{"id":"x,M;=_:Nol4(h}TFm_2$"}}}}},"next":{"block":{"type":"oled_show","id":"os6jSs2kh-FF,c2`d-h)","next":{"block":{"type":"controls_if","id":"qN9;,-(#]kE@)kR[6Uk)","inputs":{"IF0":{"block":{"type":"logic_compare","id":"eR9#)7|MN;vOpbi:w;aM","fields":{"OP":"EQ"},"inputs":{"A":{"block":{"type":"variables_get","id":"m-7pJ{vn/i=!)H:;OW~:","fields":{"VAR":{"id":"v3(@jXBkl2uoQIC_{ISq"}}}},"B":{"block":{"type":"text","id":";5Sj/|T/Q-REE)q^YSA_","fields":{"TEXT":"00"}}}}}},"DO0":{"block":{"type":"device_eye_colour_on","id":"FhRd/Eox:EL]Bnl/OP2+","inputs":{"left":{"shadow":{"type":"variables_get","id":"V2@y^1{_ht(0uhd1.Zu#","fields":{"VAR":{"id":"qx-Tk#g3SNygx}Km%?eW","name":"분","type":""}}},"block":{"type":"colour_picker","id":"q;LFdi.@MCYfJ0$aFX^$","fields":{"COLOUR":"#ff0000"}}},"right":{"shadow":{"type":"variables_get","id":"iVAD4fiTXl@dB9BjQno3","fields":{"VAR":{"id":"qx-Tk#g3SNygx}Km%?eW","name":"분","type":""}}},"block":{"type":"colour_picker","id":"_@7_~Kz_@P6/=2]Y9lRw","fields":{"COLOUR":"#ff0000"}}}},"next":{"block":{"type":"speech_tts","id":":^a,Gis@7Q9)dlr)KRrw","fields":{"voice":"main","dir":"/home/pi/code/","extension":".mp3"},"inputs":{"text":{"shadow":{"type":"text","id":",yHYDglBeY5*qR_a^F%c","fields":{"TEXT":"시간을 확인하세요"}},"block":{"type":"text_join","id":"x~-hF0)w*$VbfJiSlkRP","extraState":{"itemCount":4},"inputs":{"ADD0":{"block":{"type":"variables_get","id":"Pj1U@[TCU0w:t_tl~_pO","fields":{"VAR":{"id":"+fYZf.{A7MdWp~[695K("}}}},"ADD1":{"block":{"type":"text","id":"M%dsqTmi^xGYv)x#8Ci.","fields":{"TEXT":"시, "}}},"ADD2":{"block":{"type":"variables_get","id":"@ys+TQ}7:9:4~^Xt]?9a","fields":{"VAR":{"id":"qx-Tk#g3SNygx}Km%?eW"}}}},"ADD3":{"block":{"type":"text","id":"K;BZ9@@+rv4HEnldWkvD","fields":{"TEXT":"분 입니다."}}}}}},"filename":{"shadow":{"type":"text","id":"-fVd/(~#z)EYQ1t^o~m8","fields":{"TEXT":"voice"}}}},"next":{"block":{"type":"audio_play","id":"]+%(@/kt;OuRMN09qi_v","fields":{"dir":"/home/pi/code/","extension":".mp3"},"inputs":{"filename":{"shadow":{"type":"text","id":"s)FVVE}gS?h/ylJ8gRK`","fields":{"TEXT":"voice"}}},"volume":{"shadow":{"type":"math_number","id":"9co*IQu+Ea[iUo=FE6iu","fields":{"NUM":80}}}},"next":{"block":{"type":"device_eye_off","id":"7qj^]o58dNaE$l1T.@]."}}}}}}}}},"next":{"block":{"type":"utils_sleep","id":"2]6SWq_(~jhQa16##Zw5","inputs":{"time":{"shadow":{"type":"math_number","id":"#GG)1]}H{l{5s`1l!YMB","fields":{"NUM":1}}}},"next":{"block":{"type":"oled_clear","id":"ub16TQh9:zD)[KceWWUJ"}}}}}}}}}}}}}}}}}}}}}}}}}}}}}}}}}}]},"variables":[{"name":"현재시간","id":"wlplZ9BSF*Z|)*^h#f%["},{"name":"시분초","id":"x,M;=_:Nol4(h}TFm_2$"},{"name":"연월일","id":"5~Ymb/.DimsOP1QPM8Ms"},{"name":"초","id":"v3(@jXBkl2uoQIC_{ISq"},{"name":"분","id":"qx-Tk#g3SNygx}Km%?eW"},{"name":"시","id":"+fYZf.{A7MdWp~[695K("}]}