{"blocks":{"languageVersion":0,"blocks":[{"type":"speech_tts","id":".l@V/{MvmT#4YkAbD.qb","x":-670,"y":-850,"fields":{"voice":"main","dir":"/home/pi/code/","extension":".mp3"},"inputs":{"text":{"shadow":{"type":"text","id":"O@g$w$GPFJOLtvAJb+]f","fields":{"TEXT":"안녕하세요"}}},"filename":{"shadow":{"type":"text","id":"8d?X.U*R{-zYgrbe@6^m","fields":{"TEXT":"tts"}}}},"next":{"block":{"type":"audio_play","id":"xw@wb6|BS%84Js6g6Tp~","fields":{"dir":"/home/pi/code/","extension":".mp3"},"inputs":{"filename":{"shadow":{"type":"text","id":"s1}GVKx%03]5M-fMIP-J","fields":{"TEXT":"tts"}}},"volume":{"shadow":{"type":"math_number","id":"zMg#:kNRhJqt|!/@(C;z","fields":{"NUM":50}}}}}}}]}}