{"blocks":{"languageVersion":0,"blocks":[{"type":"device_eye_colour_on","id":"KETaj#o6z6OG@c$DR9}-","x":-1070,"y":-1490,"inputs":{"left":{"shadow":{"type":"variables_get","id":"|bbl0Z=%(NGI}R-RQOwO","fields":{"VAR":{"id":"z_6%MX+G!^aj)oo{[clK","name":"변수","type":""}}},"block":{"type":"colour_picker","id":"T}u_ZsS`.AgrXk8fKz|1","fields":{"COLOUR":"#ff0000"}}},"right":{"shadow":{"type":"variables_get","id":";A_@fX{?q@G;akMfdJpF","fields":{"VAR":{"id":"z_6%MX+G!^aj)oo{[clK","name":"변수","type":""}}},"block":{"type":"colour_picker","id":"5Py=79;8u#u[_vLdo4fb","fields":{"COLOUR":"#ff0000"}}}},"next":{"block":{"type":"utils_sleep","id":"M)?{^|O|^?~W@MMr]owO","inputs":{"time":{"block":{"type":"math_number","id":"7n-VV5n)`H]fz+k0dG#]","fields":{"NUM":3}}}},"next":{"block":{"type":"device_eye_colour_on","id":"RM8OY.A%Z3GmmJYp!_l-","inputs":{"left":{"shadow":{"type":"variables_get","id":"U%]:PyU397h44l}+(y:]","fields":{"VAR":{"id":"z_6%MX+G!^aj)oo{[clK","name":"변수","type":""}}},"block":{"type":"colour_random","id":"3xWiD1n$5-]YxjHzYNYA"}},"right":{"shadow":{"type":"variables_get","id":"mNm^@1a+OPAD+lzIMcVr","fields":{"VAR":{"id":"z_6%MX+G!^aj)oo{[clK","name":"변수","type":""}}},"block":{"type":"colour_random","id":"-6+h]=NAQ{u.)Jf)XS[p"}}}}}}}}]},"variables":[{"name":"변수","id":"z_6%MX+G!^aj)oo{[clK"}]}